atomicds/__init__.py
atomicds-0.7.0.dist-info/METADATA
atomicds-0.7.0.dist-info/WHEEL
atomicds-0.7.0.dist-info/top_level.txt
atomicds-0.7.0.dist-info/RECORD
